hakustore/__init__.py
hakustore/interface.py
hakustore/logger.py
hakustore/sql.py
hakustore/utils.py
hakustore-0.1.0.dist-info/licenses/LICENSE
hakustore-0.1.0.dist-info/METADATA
hakustore-0.1.0.dist-info/WHEEL
hakustore-0.1.0.dist-info/top_level.txt
hakustore-0.1.0.dist-info/RECORD
