Metadata-Version: 2.4
Name: hakustore
Version: 0.1.0
Summary: Persistent storage built upon one file database systems.
Author-email: "Shih-Ying Yeh(KohakuBlueLeaf)" <apolloyeh0123@gmail.com>
Project-URL: Homepage, https://github.com/KohakuBlueleaf/HakuStore
Project-URL: Repository, https://github.com/KohakuBlueleaf/HakuStore
Requires-Python: >=3.10
License-File: LICENSE
Dynamic: license-file
